songbook_maker/__init__.py
songbook_maker/combine_pdfs.py
songbook_maker/export_songs.py
songbook_maker/song_index.py
songbook_maker/uncompress_all.py
songbook_maker-1.0.dist-info/METADATA
songbook_maker-1.0.dist-info/WHEEL
songbook_maker-1.0.dist-info/licenses/LICENSE
songbook_maker-1.0.dist-info/RECORD
