Metadata-Version: 2.4
Name: songbook_maker
Version: 1.0
Summary: Tools for indexing MuseScore files and creating songbooks
Project-URL: Homepage, https://github.com/TamaMcGlinn/songbook_maker/
Project-URL: Issues, https://github.com/TamaMcGlinn/songbook_maker/issues
Author-email: Tama McGlinn <tama@anabaptist.nl>
License-Expression: MIT
License-File: LICENSE
Classifier: Operating System :: OS Independent
Classifier: Programming Language :: Python :: 3
Requires-Python: >=3.9
